{"totalCount":1,"page":1,"pageSize":50,"language":"all","results":[{"id":7,"title":{"title":"Ulike metoder","language":"nb"},"metaDescription":{"metaDescription":"Forskjellige metoder egner seg til å svare på forskjellige typer spørsmål. Her skal vi se på noen av metodene.","language":"nb"},"metaImage":{"url":"https://api.test.ndla.no/image-api/raw/id/4025","alt":"Stor hånd med forstørrelsesglass over liten mann med snakkeboble. Illustrasjon.","language":"nb"},"url":"https://api.test.ndla.no/draft-api/v1/drafts/7","contexts":[{"id":"urn:resource:1:168358","subject":"UTGÅTT - Samfunnsfag (LK06)","subjectId":"urn:subject:1:19dae192-699d-488f-8218-d81535ce3ae3","relevance":"Kjernestoff","path":"/subject:1:19dae192-699d-488f-8218-d81535ce3ae3/topic:2:179373/topic:2:170165/resource:1:168358","breadcrumbs":["UTGÅTT - Samfunnsfag (LK06)","Utforskeren ","Samfunnsfaglige tenkemåter"],"filters":[],"learningResourceType":"standard","resourceTypes":[{"id":"urn:resourcetype:subjectMaterial","name":"Fagstoff","language":"nb"},{"id":"urn:resourcetype:academicArticle","name":"Fagartikkel","language":"nb"}],"language":"all"},{"id":"urn:resource:1:168358","subject":"Samfunnskunnskap","subjectId":"urn:subject:1:470720f9-6b03-40cb-ab58-e3e130803578","relevance":"Kjernestoff","path":"/subject:1:470720f9-6b03-40cb-ab58-e3e130803578/topic:1:a317f589-7995-43aa-8b68-92182c0b23c6/topic:1:35efa357-acc7-4828-b241-cad5467d1dc6/resource:1:168358","breadcrumbs":["Samfunnskunnskap","Verktøy for utforskning","Samfunnsfaglige metoder"],"filters":[],"learningResourceType":"standard","resourceTypes":[{"id":"urn:resourcetype:subjectMaterial","name":"Fagstoff","language":"nb"},{"id":"urn:resourcetype:academicArticle","name":"Fagartikkel","language":"nb"}],"language":"all"},{"id":"urn:resource:1:168358","subject":"123-TESTFAG  - Vg1","subjectId":"urn:subject:1:5f50e974-6251-42c7-8f04-c4fabf395d0f","relevance":"Kjernestoff","path":"/subject:1:5f50e974-6251-42c7-8f04-c4fabf395d0f/topic:1:3626a87a-4d65-44fc-85b1-3edc56981e89/resource:1:168358","breadcrumbs":["123-TESTFAG  - Vg1","Test Marc Van Opstal («emne»)"],"filters":[],"learningResourceType":"standard","resourceTypes":[{"id":"urn:resourcetype:subjectMaterial","name":"Fagstoff","language":"nb"},{"id":"urn:resourcetype:academicArticle","name":"Fagartikkel","language":"nb"}],"language":"all"},{"id":"urn:resource:1:168358","subject":"123-TESTFAG  - Vg1","subjectId":"urn:subject:1:5f50e974-6251-42c7-8f04-c4fabf395d0f","relevance":"Kjernestoff","path":"/subject:1:5f50e974-6251-42c7-8f04-c4fabf395d0f/topic:1:089ff1c8-82dd-4934-b717-0d4994ed0425/resource:1:168358","breadcrumbs":["123-TESTFAG  - Vg1","Diploma of honor - testemne"],"filters":[],"learningResourceType":"standard","resourceTypes":[{"id":"urn:resourcetype:subjectMaterial","name":"Fagstoff","language":"nb"},{"id":"urn:resourcetype:academicArticle","name":"Fagartikkel","language":"nb"}],"language":"all"}],"supportedLanguages":["nb","nn"],"learningResourceType":"standard","status":{"current":"PUBLISHED","other":["IMPORTED"]},"traits":[],"score":0,"highlights":[{"field":"embedResourcesAndIds.id","matches":["<em>1</em>","<em>1</em>"]},{"field":"embedResourcesAndIds.resource","matches":["<em>concept</em>","<em>concept</em>","<em>concept</em>","<em>concept</em>"]}],"paths":["/subject:1:19dae192-699d-488f-8218-d81535ce3ae3/topic:2:179373/topic:2:170165/resource:1:168358","/subject:1:470720f9-6b03-40cb-ab58-e3e130803578/topic:1:a317f589-7995-43aa-8b68-92182c0b23c6/topic:1:35efa357-acc7-4828-b241-cad5467d1dc6/resource:1:168358","/subject:1:5f50e974-6251-42c7-8f04-c4fabf395d0f/topic:1:3626a87a-4d65-44fc-85b1-3edc56981e89/resource:1:168358","/subject:1:5f50e974-6251-42c7-8f04-c4fabf395d0f/topic:1:089ff1c8-82dd-4934-b717-0d4994ed0425/resource:1:168358"]}],"suggestions":[],"aggregations":[]}