{
  "totalCount": 24146,
  "page": 1,
  "pageSize": 10,
  "language": "nb",
  "results": [
    {
      "id": 105,
      "title": {
        "title": "Forbruk",
        "language": "nb"
      },
      "metaDescription": {
        "metaDescription": "Dersom du velger å spare penger, har du mindre til forbruk i øyeblikket, men til gjengjeld har du mer å rutte med litt lenger fram i tid.",
        "language": "nb"
      },
      "metaImage": {
        "url": "https://api.test.ndla.no/image-api/raw/id/40545",
        "alt": "Lommebok med kredittkort ved siden av en pc. Foto. ",
        "language": "nb"
      },
      "url": "https://api.test.ndla.no/draft-api/v1/drafts/105",
      "contexts": [
        {
          "id": "urn:resource:1:168453",
          "subject": "Samfunnsfag YF Vg2",
          "subjectId": "urn:subject:3",
          "path": "/subject:3/topic:1:55163/topic:1:171500/resource:1:168453",
          "breadcrumbs": [
            "Samfunnsfag YF Vg2",
            "Individ, samfunn og kultur",
            "Personlig økonomi og forbruk"
          ],
          "filters": [
            {
              "id": "urn:filter:19dae192-699d-488f-8218-d81535ce3ae3",
              "name": "SF VG1/YF VG2",
              "relevance": "Kjernestoff"
            }
          ],
          "learningResourceType": "standard",
          "resourceTypes": [
            {
              "id": "urn:resourcetype:subjectMaterial",
              "name": "Fagstoff",
              "language": "nb"
            },
            {
              "id": "urn:resourcetype:academicArticle",
              "name": "Fagartikkel",
              "language": "nb"
            }
          ],
          "language": "nb"
        },
        {
          "id": "urn:resource:1:168453",
          "subject": "Samfunnskunnskap",
          "subjectId": "urn:subject:5e750140-7d01-4b52-88ec-1daa007eeab3",
          "path": "/subject:5e750140-7d01-4b52-88ec-1daa007eeab3/topic:c70254d4-b914-42dc-8867-de34e415407e/topic:e9660de5-e1b4-4acf-bd78-888af4f219ee/resource:1:168453",
          "breadcrumbs": [
            "Samfunnskunnskap",
            "Økonomi, arbeids- og samfunnsliv",
            "Personlig økonomi og forbruk"
          ],
          "filters": [
            {
              "id": "urn:filter:470720f9-6b03-40cb-ab58-e3e130803578",
              "name": "SF VG1/YF VG2",
              "relevance": "Kjernestoff"
            }
          ],
          "learningResourceType": "standard",
          "resourceTypes": [
            {
              "id": "urn:resourcetype:subjectMaterial",
              "name": "Fagstoff",
              "language": "nb"
            },
            {
              "id": "urn:resourcetype:academicArticle",
              "name": "Fagartikkel",
              "language": "nb"
            }
          ],
          "language": "nb"
        }
      ],
      "supportedLanguages": [
        "nb",
        "nn"
      ],
      "learningResourceType": "standard",
      "status": {
        "current": "PUBLISHED",
        "other": [
          "IMPORTED"
        ]
      },
      "traits": [],
      "score": 0,
      "highlights": [
        {
          "field": "draftStatus.current",
          "matches": [
            "<em>PUBLISHED</em>"
          ]
        }
      ],
      "paths": [
        "/subject:3/topic:1:55163/topic:1:171500/resource:1:168453",
        "/subject:5e750140-7d01-4b52-88ec-1daa007eeab3/topic:c70254d4-b914-42dc-8867-de34e415407e/topic:e9660de5-e1b4-4acf-bd78-888af4f219ee/resource:1:168453"
      ],
      "revisions": [
        {
          "revisionDate": "2030-01-01T00:00:00Z",
          "note": "Automatisk revisjonsdato satt av systemet.",
          "status": "needs-revision"
        }
      ]
    },
    {
      "id": 108,
      "title": {
        "title": "Handel og forbruk for framtida",
        "language": "nb"
      },
      "metaDescription": {
        "metaDescription": "Hvis alle mennesker i verden skulle forbruke like mye som vi gjør i dag, vil utslippene øke og økosystemet raskt komme i ubalanse.",
        "language": "nb"
      },
      "metaImage": {
        "url": "https://api.test.ndla.no/image-api/raw/id/28268",
        "alt": "Tekstilfabrikk i Kambodsja. Foto. ",
        "language": "nb"
      },
      "url": "https://api.test.ndla.no/draft-api/v1/drafts/108",
      "contexts": [
        {
          "id": "urn:resource:1:168459",
          "subject": "Samfunnsfag YF Vg2",
          "subjectId": "urn:subject:3",
          "path": "/subject:3/topic:1:55163/topic:1:171500/resource:1:168459",
          "breadcrumbs": [
            "Samfunnsfag YF Vg2",
            "Individ, samfunn og kultur",
            "Personlig økonomi og forbruk"
          ],
          "filters": [
            {
              "id": "urn:filter:19dae192-699d-488f-8218-d81535ce3ae3",
              "name": "SF VG1/YF VG2",
              "relevance": "Kjernestoff"
            }
          ],
          "learningResourceType": "standard",
          "resourceTypes": [
            {
              "id": "urn:resourcetype:subjectMaterial",
              "name": "Fagstoff",
              "language": "nb"
            },
            {
              "id": "urn:resourcetype:academicArticle",
              "name": "Fagartikkel",
              "language": "nb"
            }
          ],
          "language": "nb"
        },
        {
          "id": "urn:resource:1:168459",
          "subject": "Samfunnskunnskap",
          "subjectId": "urn:subject:5e750140-7d01-4b52-88ec-1daa007eeab3",
          "path": "/subject:5e750140-7d01-4b52-88ec-1daa007eeab3/topic:c70254d4-b914-42dc-8867-de34e415407e/topic:e9660de5-e1b4-4acf-bd78-888af4f219ee/resource:1:168459",
          "breadcrumbs": [
            "Samfunnskunnskap",
            "Økonomi, arbeids- og samfunnsliv",
            "Personlig økonomi og forbruk"
          ],
          "filters": [
            {
              "id": "urn:filter:470720f9-6b03-40cb-ab58-e3e130803578",
              "name": "SF VG1/YF VG2",
              "relevance": "Kjernestoff"
            }
          ],
          "learningResourceType": "standard",
          "resourceTypes": [
            {
              "id": "urn:resourcetype:subjectMaterial",
              "name": "Fagstoff",
              "language": "nb"
            },
            {
              "id": "urn:resourcetype:academicArticle",
              "name": "Fagartikkel",
              "language": "nb"
            }
          ],
          "language": "nb"
        }
      ],
      "supportedLanguages": [
        "nb",
        "nn"
      ],
      "learningResourceType": "standard",
      "status": {
        "current": "PUBLISHED",
        "other": [
          "IMPORTED"
        ]
      },
      "traits": [],
      "score": 0,
      "highlights": [
        {
          "field": "draftStatus.current",
          "matches": [
            "<em>PUBLISHED</em>"
          ]
        }
      ],
      "paths": [
        "/subject:3/topic:1:55163/topic:1:171500/resource:1:168459",
        "/subject:5e750140-7d01-4b52-88ec-1daa007eeab3/topic:c70254d4-b914-42dc-8867-de34e415407e/topic:e9660de5-e1b4-4acf-bd78-888af4f219ee/resource:1:168459"
      ],
      "revisions": [
        {
          "revisionDate": "2030-01-01T00:00:00Z",
          "note": "Automatisk revisjonsdato satt av systemet.",
          "status": "needs-revision"
        }
      ]
    },
    {
      "id": 110,
      "title": {
        "title": "Budsjettkalkulator",
        "language": "nb"
      },
      "metaDescription": {
        "metaDescription": "Her kan du simulere din personlige økonomi.",
        "language": "nb"
      },
      "url": "https://api.test.ndla.no/draft-api/v1/drafts/110",
      "contexts": [
        {
          "id": "urn:resource:1:127561",
          "subject": "Samfunnsfag YF Vg2",
          "subjectId": "urn:subject:3",
          "path": "/subject:3/topic:1:55163/topic:1:171500/resource:1:127561",
          "breadcrumbs": [
            "Samfunnsfag YF Vg2",
            "Individ, samfunn og kultur",
            "Personlig økonomi og forbruk"
          ],
          "filters": [
            {
              "id": "urn:filter:19dae192-699d-488f-8218-d81535ce3ae3",
              "name": "SF VG1/YF VG2",
              "relevance": "Tilleggsstoff"
            }
          ],
          "learningResourceType": "standard",
          "resourceTypes": [
            {
              "id": "urn:resourcetype:subjectMaterial",
              "name": "Fagstoff",
              "language": "nb"
            },
            {
              "id": "urn:resourcetype:simulation",
              "name": "Simulering",
              "language": "nb"
            }
          ],
          "language": "nb"
        },
        {
          "id": "urn:resource:1:127561",
          "subject": "Service og samferdsel Vg1 2019-20",
          "subjectId": "urn:subject:12",
          "path": "/subject:12/topic:1:184105/topic:1:184119/resource:1:127561",
          "breadcrumbs": [
            "Service og samferdsel Vg1 2019-20",
            "Økonomi",
            "Budsjettering"
          ],
          "filters": [
            {
              "id": "urn:filter:df8344b6-ad86-44be-b6b2-d61b3526ed29",
              "name": "Administrasjon og økonomi",
              "relevance": "Tilleggsstoff"
            }
          ],
          "learningResourceType": "standard",
          "resourceTypes": [
            {
              "id": "urn:resourcetype:subjectMaterial",
              "name": "Fagstoff",
              "language": "nb"
            },
            {
              "id": "urn:resourcetype:simulation",
              "name": "Simulering",
              "language": "nb"
            }
          ],
          "language": "nb"
        },
        {
          "id": "urn:resource:1:127561",
          "subject": "Praktisk matematikk",
          "subjectId": "urn:subject:29",
          "path": "/subject:29/topic:1:163965/resource:1:127561",
          "breadcrumbs": [
            "Praktisk matematikk",
            "Økonomi"
          ],
          "filters": [
            {
              "id": "urn:filter:3fa5baa7-d8d8-4b50-98a0-411bbcef13fa",
              "name": "1P",
              "relevance": "Kjernestoff"
            }
          ],
          "learningResourceType": "standard",
          "resourceTypes": [
            {
              "id": "urn:resourcetype:subjectMaterial",
              "name": "Fagstoff",
              "language": "nb"
            },
            {
              "id": "urn:resourcetype:simulation",
              "name": "Simulering",
              "language": "nb"
            }
          ],
          "language": "nb"
        },
        {
          "id": "urn:resource:1:127561",
          "subject": "Matematikk for yrkesfaglige programmer",
          "subjectId": "urn:subject:30",
          "path": "/subject:30/topic:2:1:163965/resource:1:127561",
          "breadcrumbs": [
            "Matematikk for yrkesfaglige programmer",
            "Økonomi"
          ],
          "filters": [
            {
              "id": "urn:filter:04ad8a02-856c-417c-8a58-d2f293bf788d",
              "name": "1P-Y",
              "relevance": "Kjernestoff"
            }
          ],
          "learningResourceType": "standard",
          "resourceTypes": [
            {
              "id": "urn:resourcetype:subjectMaterial",
              "name": "Fagstoff",
              "language": "nb"
            },
            {
              "id": "urn:resourcetype:simulation",
              "name": "Simulering",
              "language": "nb"
            }
          ],
          "language": "nb"
        }
      ],
      "supportedLanguages": [
        "nb",
        "nn"
      ],
      "learningResourceType": "standard",
      "status": {
        "current": "PUBLISHED",
        "other": [
          "IMPORTED"
        ]
      },
      "traits": [
        "H5P"
      ],
      "score": 0,
      "highlights": [
        {
          "field": "draftStatus.current",
          "matches": [
            "<em>PUBLISHED</em>"
          ]
        }
      ],
      "paths": [
        "/subject:3/topic:1:55163/topic:1:171500/resource:1:127561",
        "/subject:12/topic:1:184105/topic:1:184119/resource:1:127561",
        "/subject:29/topic:1:163965/resource:1:127561",
        "/subject:30/topic:2:1:163965/resource:1:127561"
      ],
      "revisions": [
        {
          "revisionDate": "2030-01-01T00:00:00Z",
          "note": "Automatisk revisjonsdato satt av systemet.",
          "status": "needs-revision"
        }
      ]
    },
    {
      "id": 119,
      "title": {
        "title": "Hva styrer partiene etter?",
        "language": "nb"
      },
      "metaDescription": {
        "metaDescription": "De politiske partiene har to typer programmer: prinsipprogrammer og valgprogrammer.",
        "language": "nb"
      },
      "metaImage": {
        "url": "https://api.test.ndla.no/image-api/raw/id/5472",
        "alt": "Norske partiledere. Fotokollasj.",
        "language": "nb"
      },
      "url": "https://api.test.ndla.no/draft-api/v1/drafts/119",
      "contexts": [
        {
          "id": "urn:resource:1:84623",
          "subject": "Samfunnsfag YF Vg2",
          "subjectId": "urn:subject:3",
          "path": "/subject:3/topic:1:168542/topic:1:173292/resource:1:84623",
          "breadcrumbs": [
            "Samfunnsfag YF Vg2",
            "Politikk og demokrati",
            "Det demokratiske systemet i Norge"
          ],
          "filters": [
            {
              "id": "urn:filter:19dae192-699d-488f-8218-d81535ce3ae3",
              "name": "SF VG1/YF VG2",
              "relevance": "Kjernestoff"
            }
          ],
          "learningResourceType": "standard",
          "resourceTypes": [
            {
              "id": "urn:resourcetype:subjectMaterial",
              "name": "Fagstoff",
              "language": "nb"
            },
            {
              "id": "urn:resourcetype:academicArticle",
              "name": "Fagartikkel",
              "language": "nb"
            }
          ],
          "language": "nb"
        }
      ],
      "supportedLanguages": [
        "nb",
        "nn"
      ],
      "learningResourceType": "standard",
      "status": {
        "current": "PUBLISHED",
        "other": [
          "IMPORTED"
        ]
      },
      "traits": [],
      "score": 0,
      "highlights": [
        {
          "field": "draftStatus.current",
          "matches": [
            "<em>PUBLISHED</em>"
          ]
        }
      ],
      "paths": [
        "/subject:3/topic:1:168542/topic:1:173292/resource:1:84623"
      ],
      "revisions": [
        {
          "revisionDate": "2030-01-01T00:00:00Z",
          "note": "Automatisk revisjonsdato satt av systemet.",
          "status": "needs-revision"
        }
      ],
      "revisions": [
        {
          "revisionDate": "2030-01-01T00:00:00Z",
          "note": "Automatisk revisjonsdato satt av systemet.",
          "status": "needs-revision"
        }
      ]
    },
    {
      "id": 120,
      "title": {
        "title": "Regjeringa",
        "language": "nb"
      },
      "metaDescription": {
        "metaDescription": "Etter et stortingsvalg er det formelt sett kongen som peker ut hvem som skal danne regjering.",
        "language": "nb"
      },
      "metaImage": {
        "url": "https://api.test.ndla.no/image-api/raw/id/40549",
        "alt": "  ",
        "language": "nb"
      },
      "url": "https://api.test.ndla.no/draft-api/v1/drafts/120",
      "contexts": [
        {
          "id": "urn:resource:1:168552",
          "subject": "Samfunnsfag YF Vg2",
          "subjectId": "urn:subject:3",
          "path": "/subject:3/topic:1:168542/topic:1:173292/resource:1:168552",
          "breadcrumbs": [
            "Samfunnsfag YF Vg2",
            "Politikk og demokrati",
            "Det demokratiske systemet i Norge"
          ],
          "filters": [
            {
              "id": "urn:filter:19dae192-699d-488f-8218-d81535ce3ae3",
              "name": "SF VG1/YF VG2",
              "relevance": "Kjernestoff"
            }
          ],
          "learningResourceType": "standard",
          "resourceTypes": [
            {
              "id": "urn:resourcetype:subjectMaterial",
              "name": "Fagstoff",
              "language": "nb"
            },
            {
              "id": "urn:resourcetype:academicArticle",
              "name": "Fagartikkel",
              "language": "nb"
            }
          ],
          "language": "nb"
        },
        {
          "id": "urn:resource:1:168552",
          "subject": "Samfunnskunnskap",
          "subjectId": "urn:subject:5e750140-7d01-4b52-88ec-1daa007eeab3",
          "path": "/subject:5e750140-7d01-4b52-88ec-1daa007eeab3/topic:3d26f57e-a8c9-45e5-bc57-2d31df53f969/topic:27f37dfa-783e-4c3e-a52e-406ab0741b25/resource:1:168552",
          "breadcrumbs": [
            "Samfunnskunnskap",
            "Demokrati og medborgerskap",
            "Det norske demokratiet"
          ],
          "filters": [
            {
              "id": "urn:filter:470720f9-6b03-40cb-ab58-e3e130803578",
              "name": "SF VG1/YF VG2",
              "relevance": "Kjernestoff"
            }
          ],
          "learningResourceType": "standard",
          "resourceTypes": [
            {
              "id": "urn:resourcetype:subjectMaterial",
              "name": "Fagstoff",
              "language": "nb"
            },
            {
              "id": "urn:resourcetype:academicArticle",
              "name": "Fagartikkel",
              "language": "nb"
            }
          ],
          "language": "nb"
        }
      ],
      "supportedLanguages": [
        "nb",
        "nn"
      ],
      "learningResourceType": "standard",
      "status": {
        "current": "PUBLISHED",
        "other": [
          "IMPORTED"
        ]
      },
      "traits": [],
      "score": 0,
      "highlights": [
        {
          "field": "draftStatus.current",
          "matches": [
            "<em>PUBLISHED</em>"
          ]
        }
      ],
      "paths": [
        "/subject:3/topic:1:168542/topic:1:173292/resource:1:168552",
        "/subject:5e750140-7d01-4b52-88ec-1daa007eeab3/topic:3d26f57e-a8c9-45e5-bc57-2d31df53f969/topic:27f37dfa-783e-4c3e-a52e-406ab0741b25/resource:1:168552"
      ],
      "revisions": [
        {
          "revisionDate": "2030-01-01T00:00:00Z",
          "note": "Automatisk revisjonsdato satt av systemet.",
          "status": "needs-revision"
        }
      ]
    },
    {
      "id": 123,
      "title": {
        "title": "Året 2030 – valget er ditt",
        "language": "nb"
      },
      "metaDescription": {
        "metaDescription": "Tenk deg inn i framtida til året 2030. Hvordan tror du Norge og verden ser ut da?",
        "language": "nb"
      },
      "metaImage": {
        "url": "https://api.test.ndla.no/image-api/raw/id/40551",
        "alt": "Noen av bygningene i Barcode-rekken i Operakvarteret i Oslo. Foto. ",
        "language": "nb"
      },
      "url": "https://api.test.ndla.no/draft-api/v1/drafts/123",
      "contexts": [
        {
          "id": "urn:resource:1:11531",
          "subject": "Samfunnsfag YF Vg2",
          "subjectId": "urn:subject:3",
          "path": "/subject:3/topic:1:168542/topic:1:126082/resource:1:11531",
          "breadcrumbs": [
            "Samfunnsfag YF Vg2",
            "Politikk og demokrati",
            "Valgstoff på NDLA"
          ],
          "filters": [
            {
              "id": "urn:filter:19dae192-699d-488f-8218-d81535ce3ae3",
              "name": "SF VG1/YF VG2",
              "relevance": "Kjernestoff"
            }
          ],
          "learningResourceType": "standard",
          "resourceTypes": [
            {
              "id": "urn:resourcetype:tasksAndActivities",
              "name": "Oppgaver og aktiviteter",
              "language": "nb"
            },
            {
              "id": "urn:resourcetype:task",
              "name": "Oppgave",
              "language": "nb"
            }
          ],
          "language": "nb"
        },
        {
          "id": "urn:resource:1:11531",
          "subject": "Samfunnskunnskap",
          "subjectId": "urn:subject:5e750140-7d01-4b52-88ec-1daa007eeab3",
          "path": "/subject:5e750140-7d01-4b52-88ec-1daa007eeab3/topic:3d26f57e-a8c9-45e5-bc57-2d31df53f969/topic:41d1aefe-880f-4f59-873f-c983f34b8a26/resource:1:11531",
          "breadcrumbs": [
            "Samfunnskunnskap",
            "Demokrati og medborgerskap",
            "Medborgerskap og makt"
          ],
          "filters": [
            {
              "id": "urn:filter:470720f9-6b03-40cb-ab58-e3e130803578",
              "name": "SF VG1/YF VG2",
              "relevance": "Kjernestoff"
            }
          ],
          "learningResourceType": "standard",
          "resourceTypes": [
            {
              "id": "urn:resourcetype:tasksAndActivities",
              "name": "Oppgaver og aktiviteter",
              "language": "nb"
            },
            {
              "id": "urn:resourcetype:task",
              "name": "Oppgave",
              "language": "nb"
            }
          ],
          "language": "nb"
        }
      ],
      "supportedLanguages": [
        "nb",
        "nn"
      ],
      "learningResourceType": "standard",
      "status": {
        "current": "PUBLISHED",
        "other": [
          "IMPORTED"
        ]
      },
      "traits": [],
      "score": 0,
      "highlights": [
        {
          "field": "draftStatus.current",
          "matches": [
            "<em>PUBLISHED</em>"
          ]
        }
      ],
      "paths": [
        "/subject:3/topic:1:168542/topic:1:126082/resource:1:11531",
        "/subject:5e750140-7d01-4b52-88ec-1daa007eeab3/topic:3d26f57e-a8c9-45e5-bc57-2d31df53f969/topic:41d1aefe-880f-4f59-873f-c983f34b8a26/resource:1:11531"
      ],
      "revisions": [
        {
          "revisionDate": "2030-01-01T00:00:00Z",
          "note": "Automatisk revisjonsdato satt av systemet.",
          "status": "needs-revision"
        }
      ]
    },
    {
      "id": 126,
      "title": {
        "title": "Oppgave: Den viktige sperregrensa",
        "language": "nb"
      },
      "metaDescription": {
        "metaDescription": "Spørsmål til teksten «Den viktige sperregrensa».",
        "language": "nb"
      },
      "url": "https://api.test.ndla.no/draft-api/v1/drafts/126",
      "contexts": [],
      "supportedLanguages": [
        "nb",
        "nn"
      ],
      "learningResourceType": "standard",
      "status": {
        "current": "PUBLISHED",
        "other": [
          "IMPORTED"
        ]
      },
      "traits": [],
      "score": 0,
      "highlights": [
        {
          "field": "draftStatus.current",
          "matches": [
            "<em>PUBLISHED</em>"
          ]
        }
      ],
      "paths": [],
      "revisions": [
        {
          "revisionDate": "2030-01-01T00:00:00Z",
          "note": "Automatisk revisjonsdato satt av systemet.",
          "status": "needs-revision"
        }
      ]
    },
    {
      "id": 129,
      "title": {
        "title": "Skolevalget",
        "language": "nb"
      },
      "metaDescription": {
        "metaDescription": "Før skolevalget møtes unge politikere til debatt og valgtorg ved landets videregående skoler. Deretter holdes det et skolevalg.",
        "language": "nb"
      },
      "metaImage": {
        "url": "https://api.test.ndla.no/image-api/raw/id/12103",
        "alt": "Skoledebatt Oslo katedralskole. Foto.",
        "language": "nb"
      },
      "url": "https://api.test.ndla.no/draft-api/v1/drafts/129",
      "contexts": [
        {
          "id": "urn:resource:1:126300",
          "subject": "Samfunnsfag YF Vg2",
          "subjectId": "urn:subject:3",
          "path": "/subject:3/topic:1:168542/topic:1:126082/resource:1:126300",
          "breadcrumbs": [
            "Samfunnsfag YF Vg2",
            "Politikk og demokrati",
            "Valgstoff på NDLA"
          ],
          "filters": [
            {
              "id": "urn:filter:19dae192-699d-488f-8218-d81535ce3ae3",
              "name": "SF VG1/YF VG2",
              "relevance": "Kjernestoff"
            }
          ],
          "learningResourceType": "standard",
          "resourceTypes": [
            {
              "id": "urn:resourcetype:subjectMaterial",
              "name": "Fagstoff",
              "language": "nb"
            },
            {
              "id": "urn:resourcetype:academicArticle",
              "name": "Fagartikkel",
              "language": "nb"
            }
          ],
          "language": "nb"
        },
        {
          "id": "urn:resource:1:126300",
          "subject": "Samfunnskunnskap",
          "subjectId": "urn:subject:5e750140-7d01-4b52-88ec-1daa007eeab3",
          "path": "/subject:5e750140-7d01-4b52-88ec-1daa007eeab3/topic:3d26f57e-a8c9-45e5-bc57-2d31df53f969/topic:27f37dfa-783e-4c3e-a52e-406ab0741b25/resource:1:126300",
          "breadcrumbs": [
            "Samfunnskunnskap",
            "Demokrati og medborgerskap",
            "Det norske demokratiet"
          ],
          "filters": [
            {
              "id": "urn:filter:470720f9-6b03-40cb-ab58-e3e130803578",
              "name": "SF VG1/YF VG2",
              "relevance": "Kjernestoff"
            }
          ],
          "learningResourceType": "standard",
          "resourceTypes": [
            {
              "id": "urn:resourcetype:subjectMaterial",
              "name": "Fagstoff",
              "language": "nb"
            },
            {
              "id": "urn:resourcetype:academicArticle",
              "name": "Fagartikkel",
              "language": "nb"
            }
          ],
          "language": "nb"
        }
      ],
      "supportedLanguages": [
        "nb",
        "nn"
      ],
      "learningResourceType": "standard",
      "status": {
        "current": "PUBLISHED",
        "other": [
          "IMPORTED"
        ]
      },
      "traits": [],
      "score": 0,
      "highlights": [
        {
          "field": "draftStatus.current",
          "matches": [
            "<em>PUBLISHED</em>"
          ]
        }
      ],
      "paths": [
        "/subject:3/topic:1:168542/topic:1:126082/resource:1:126300",
        "/subject:5e750140-7d01-4b52-88ec-1daa007eeab3/topic:3d26f57e-a8c9-45e5-bc57-2d31df53f969/topic:27f37dfa-783e-4c3e-a52e-406ab0741b25/resource:1:126300"
      ],
      "revisions": [
        {
          "revisionDate": "2030-01-01T00:00:00Z",
          "note": "Automatisk revisjonsdato satt av systemet.",
          "status": "needs-revision"
        }
      ]
    },
    {
      "id": 130,
      "title": {
        "title": "Politikk er påvirkning",
        "language": "nb"
      },
      "metaDescription": {
        "metaDescription": "Det er vi som bor i landet, som skaper politikk gjennom det engasjementet vi viser. Vi har flere kanaler for slik politisk innflytelse.",
        "language": "nb"
      },
      "metaImage": {
        "url": "https://api.test.ndla.no/image-api/raw/id/29125",
        "alt": "",
        "language": "nb"
      },
      "url": "https://api.test.ndla.no/draft-api/v1/drafts/130",
      "contexts": [
        {
          "id": "urn:topic:1:172420",
          "subject": "Samfunnsfag YF Vg2",
          "subjectId": "urn:subject:3",
          "path": "/subject:3/topic:1:168542/topic:1:172420",
          "breadcrumbs": [
            "Samfunnsfag YF Vg2",
            "Politikk og demokrati"
          ],
          "filters": [
            {
              "id": "urn:filter:19dae192-699d-488f-8218-d81535ce3ae3",
              "name": "SF VG1/YF VG2",
              "relevance": "Kjernestoff"
            }
          ],
          "learningResourceType": "topic-article",
          "resourceTypes": [],
          "language": "nb"
        }
      ],
      "supportedLanguages": [
        "nb",
        "nn"
      ],
      "learningResourceType": "topic-article",
      "status": {
        "current": "PUBLISHED",
        "other": [
          "IMPORTED"
        ]
      },
      "traits": [],
      "score": 0,
      "highlights": [
        {
          "field": "draftStatus.current",
          "matches": [
            "<em>PUBLISHED</em>"
          ]
        }
      ],
      "paths": [
        "/subject:3/topic:1:168542/topic:1:172420"
      ],
      "revisions": [
        {
          "revisionDate": "2030-01-01T00:00:00Z",
          "note": "Automatisk revisjonsdato satt av systemet.",
          "status": "needs-revision"
        }
      ]
    },
    {
      "id": 132,
      "title": {
        "title": "Riksforsamlinga med Are Kalvø: om folkeaksjonar, del 1",
        "language": "nb"
      },
      "metaDescription": {
        "metaDescription": "Video",
        "language": "nb"
      },
      "url": "https://api.test.ndla.no/draft-api/v1/drafts/132",
      "contexts": [
        {
          "id": "urn:resource:1:121328",
          "subject": "Samfunnsfag YF Vg2",
          "subjectId": "urn:subject:3",
          "path": "/subject:3/topic:1:168542/topic:1:172420/resource:1:121328",
          "breadcrumbs": [
            "Samfunnsfag YF Vg2",
            "Politikk og demokrati",
            "Politikk er påvirkning"
          ],
          "filters": [
            {
              "id": "urn:filter:19dae192-699d-488f-8218-d81535ce3ae3",
              "name": "SF VG1/YF VG2",
              "relevance": "Tilleggsstoff"
            }
          ],
          "learningResourceType": "standard",
          "resourceTypes": [
            {
              "id": "urn:resourcetype:subjectMaterial",
              "name": "Fagstoff",
              "language": "nb"
            },
            {
              "id": "urn:resourcetype:movieAndClip",
              "name": "Film og filmklipp",
              "language": "nb"
            }
          ],
          "language": "nb"
        }
      ],
      "supportedLanguages": [
        "nb"
      ],
      "learningResourceType": "standard",
      "status": {
        "current": "PUBLISHED",
        "other": [
          "IMPORTED"
        ]
      },
      "traits": [
        "VIDEO"
      ],
      "score": 0,
      "highlights": [
        {
          "field": "draftStatus.current",
          "matches": [
            "<em>PUBLISHED</em>"
          ]
        }
      ],
      "paths": [
        "/subject:3/topic:1:168542/topic:1:172420/resource:1:121328"
      ],
      "revisions": [
        {
          "revisionDate": "2030-01-01T00:00:00Z",
          "note": "Automatisk revisjonsdato satt av systemet.",
          "status": "needs-revision"
        }
      ]
    }
  ],
  "suggestions": [],
  "aggregations": []
}
