{"id":"26827","metaUrl":"https://test.api.ndla.no/image-api/v2/images/26827","title":{"title":"   FARAWELL MY CONCUBINE (1993).  ","language":"unknown"},"alttext":{"alttext":"Bilde 2 av Farvel min konkubine","language":"unknown"},"imageUrl":"https://test.api.ndla.no/image-api/raw/20130917-154443-8.jpg","size":373446,"contentType":"image/jpeg","copyright":{"license":{"license":"CC-BY-NC-SA-4.0","description":"Creative Commons Attribution-NonCommercial-ShareAlike 4.0 International","url":"https://creativecommons.org/licenses/by-nc-sa/4.0/"},"origin":"http://www.scanpix.no","creators":[],"processors":[],"rightsholders":[{"type":"Supplier","name":"BEIJING FILM STUDIO/CHINA FILM CORP./MAVERICK PICTURES / Album"},{"type":"Supplier","name":"NTB scanpix"}]},"tags":{"tags":["bilde","film","kinesisk"],"language":"nb"},"caption":{"caption":"","language":"nb"},"supportedLanguages":["unknown","nb","nn","en","de"]}