{"totalCount":67343,"page":2,"pageSize":10,"language":"*","results":[{"id":"70","metaUrl":"https://api.test.ndla.no/image-api/v3/images/70","title":{"title":"Tabell: finansiering skoleinternatet i Kautokeino","language":"und"},"alttext":{"alttext":"Oversikt over finansiering av skoleinternatet i Kautokeino. Tabell. ","language":"und"},"copyright":{"license":{"license":"CC-BY-NC-ND-4.0","description":"Creative Commons Attribution-NonCommercial-NoDerivs 4.0 International","url":"https://creativecommons.org/licenses/by-nc-nd/4.0/"},"origin":"Test User","creators":[{"type":"Writer","name":"Test writer"},{"type":"writer","name":"Test writeerrr"}],"processors":[],"rightsholders":[]},"tags":{"tags":["kautokeino","finansiering","internat","samer","skolehistorie"],"language":"nb"},"caption":{"caption":"","language":"nb"},"supportedLanguages":["nb","nn","en","und"],"created":"2017-05-08T13:25:26.000Z","createdBy":"content-import-client","modelRelease":"not-set","image":{"fileName":"finansiering_skoleinternatet.jpg","size":36211,"contentType":"image/jpeg","imageUrl":"https://api.test.ndla.no/image-api/raw/finansiering_skoleinternatet.jpg","dimensions":{"width":617,"height":199},"language":"nb"}},{"id":"74","metaUrl":"https://api.test.ndla.no/image-api/v3/images/74","title":{"title":"Folk som står i ring og skåler på Oktoberfest","language":"und"},"alttext":{"alttext":"Yngre mennesker som står i ring og skåler på Oktoberfest. Foto.","language":"und"},"copyright":{"license":{"license":"CC-BY-NC-ND-4.0","description":"Creative Commons Attribution-NonCommercial-NoDerivs 4.0 International","url":"https://creativecommons.org/licenses/by-nc-nd/4.0/"},"origin":"Test User","creators":[{"type":"Writer","name":"Test writer"},{"type":"writer","name":"Test writeerrr"}],"processors":[],"rightsholders":[]},"tags":{"tags":["münchen","oktoberfest","øl"],"language":"nb"},"caption":{"caption":"","language":"nb"},"supportedLanguages":["nb","nn","en","de","und"],"created":"2017-05-08T13:25:26.000Z","createdBy":"content-import-client","modelRelease":"not-set","image":{"fileName":"oktoberfest_festival_46740455_0_0.jpg","size":2953345,"contentType":"image/jpeg","imageUrl":"https://api.test.ndla.no/image-api/raw/oktoberfest_festival_46740455_0_0.jpg","dimensions":{"width":4096,"height":2732},"language":"nb"}},{"id":"107","metaUrl":"https://api.test.ndla.no/image-api/v3/images/107","title":{"title":"Skjermdump – Hva gjør en forsker?","language":"und"},"alttext":{"alttext":"Bilde av filmer \"Hva gjør en forsker?\"","language":"und"},"copyright":{"license":{"license":"CC-BY-NC-ND-4.0","description":"Creative Commons Attribution-NonCommercial-NoDerivs 4.0 International","url":"https://creativecommons.org/licenses/by-nc-nd/4.0/"},"origin":"Test User","creators":[{"type":"Writer","name":"Test writer"},{"type":"writer","name":"Test writeerrr"}],"processors":[],"rightsholders":[]},"tags":{"tags":[],"language":"nb"},"caption":{"caption":"","language":"nb"},"supportedLanguages":["und"],"created":"2019-06-17T14:17:18.000Z","createdBy":"r0gHb9Xg3li4yyXv0QSGQczV3bviakrT","modelRelease":"not-set","image":{"fileName":"/skjermdump-hva_gjor_en_forsker_1.jpg","size":80383,"contentType":"image/jpeg","imageUrl":"https://api.test.ndla.no/image-api/raw/skjermdump-hva_gjor_en_forsker_1.jpg","dimensions":{"width":853,"height":477},"language":"und"}},{"id":"153","metaUrl":"https://api.test.ndla.no/image-api/v3/images/153","title":{"title":"Okse av rasen Simmental","language":"und"},"alttext":{"alttext":"","language":"nb"},"copyright":{"license":{"license":"CC-BY-NC-ND-4.0","description":"Creative Commons Attribution-NonCommercial-NoDerivs 4.0 International","url":"https://creativecommons.org/licenses/by-nc-nd/4.0/"},"origin":"Test User","creators":[{"type":"Writer","name":"Test writer"},{"type":"writer","name":"Test writeerrr"}],"processors":[],"rightsholders":[]},"tags":{"tags":["husdyravl","kjøttfe","storfe"],"language":"nb"},"caption":{"caption":"","language":"nb"},"supportedLanguages":["nb","nn","en","und"],"created":"2017-05-08T13:25:26.000Z","createdBy":"content-import-client","modelRelease":"not-set","image":{"fileName":"20041013sg011_1.jpg","size":346061,"contentType":"image/jpeg","imageUrl":"https://api.test.ndla.no/image-api/raw/20041013sg011_1.jpg","dimensions":{"width":920,"height":613},"language":"nb"}},{"id":"89","metaUrl":"https://api.test.ndla.no/image-api/v3/images/89","title":{"title":"Protokol over idømte bøter for skoleforsømmelse, s 21, 1918","language":"und"},"alttext":{"alttext":"Protokoll over ilagte bøter for skoleforsømmelse, Kautokeino 1918. Foto av kilde.","language":"und"},"copyright":{"license":{"license":"CC-BY-NC-ND-4.0","description":"Creative Commons Attribution-NonCommercial-NoDerivs 4.0 International","url":"https://creativecommons.org/licenses/by-nc-nd/4.0/"},"origin":"Test User","creators":[{"type":"Writer","name":"Test writer"},{"type":"writer","name":"Test writeerrr"}],"processors":[],"rightsholders":[]},"tags":{"tags":["source","protocol","sami history"],"language":"und"},"caption":{"caption":"","language":"nb"},"supportedLanguages":["und"],"created":"2018-11-03T11:04:44.000Z","createdBy":"r0gHb9Xg3li4yyXv0QSGQczV3bviakrT","modelRelease":"not-set","image":{"fileName":"/side_21_protokollen.jpg","size":2220250,"contentType":"image/jpeg","imageUrl":"https://api.test.ndla.no/image-api/raw/side_21_protokollen.jpg","dimensions":{"width":5190,"height":4172},"language":"und"}},{"id":"90","metaUrl":"https://api.test.ndla.no/image-api/v3/images/90","title":{"title":"Protokol over ilagte bøter for skoleforsømmelse, Kautokeino skolestyre","language":"und"},"alttext":{"alttext":"Beskjært forside fra protokoll over ilagte bøter for skoleforsømmelse, Kautokeino skolestyre 1913-1930. Foto av kilde. ","language":"und"},"copyright":{"license":{"license":"CC-BY-NC-ND-4.0","description":"Creative Commons Attribution-NonCommercial-NoDerivs 4.0 International","url":"https://creativecommons.org/licenses/by-nc-nd/4.0/"},"origin":"Test User","creators":[{"type":"Writer","name":"Test writer"},{"type":"writer","name":"Test writeerrr"}],"processors":[],"rightsholders":[]},"tags":{"tags":["source","protocol","sami people"],"language":"und"},"caption":{"caption":"","language":"nb"},"supportedLanguages":["und"],"created":"2018-11-03T11:03:03.000Z","createdBy":"r0gHb9Xg3li4yyXv0QSGQczV3bviakrT","modelRelease":"not-set","image":{"fileName":"/forside_protokoll_kautokeino_skolestyre.jpg","size":1247062,"contentType":"image/jpeg","imageUrl":"https://api.test.ndla.no/image-api/raw/forside_protokoll_kautokeino_skolestyre.jpg","dimensions":{"width":2104,"height":2766},"language":"und"}},{"id":"103","metaUrl":"https://api.test.ndla.no/image-api/v3/images/103","title":{"title":"Skihopping på landstasjonen Grytviken i Sør-Georgia","language":"und"},"alttext":{"alttext":"Skihopping på landstasjonen Grytviken i Sør-Georgia. Foto. ","language":"und"},"copyright":{"license":{"license":"CC-BY-NC-ND-4.0","description":"Creative Commons Attribution-NonCommercial-NoDerivs 4.0 International","url":"https://creativecommons.org/licenses/by-nc-nd/4.0/"},"origin":"Test User","creators":[{"type":"Writer","name":"Test writer"},{"type":"writer","name":"Test writeerrr"}],"processors":[],"rightsholders":[]},"tags":{"tags":["grytviken","sør-georgia","hvalfangst","landstasjon","skihopping"],"language":"nb"},"caption":{"caption":"","language":"nb"},"supportedLanguages":["nb","nn","en","und"],"created":"2017-05-08T13:25:26.000Z","createdBy":"content-import-client","modelRelease":"not-set","image":{"fileName":"ny_foto-andersson023_0.jpg","size":1973332,"contentType":"image/jpeg","imageUrl":"https://api.test.ndla.no/image-api/raw/ny_foto-andersson023_0.jpg","dimensions":{"width":3000,"height":2200},"language":"nb"}},{"id":"128","metaUrl":"https://api.test.ndla.no/image-api/v3/images/128","title":{"title":"Poretrykksdiagram","language":"und"},"alttext":{"alttext":"Poretrykksdiagram. Illustrasjon.","language":"und"},"copyright":{"license":{"license":"CC-BY-NC-ND-4.0","description":"Creative Commons Attribution-NonCommercial-NoDerivs 4.0 International","url":"https://creativecommons.org/licenses/by-nc-nd/4.0/"},"origin":"Test User","creators":[{"type":"Writer","name":"Test writer"},{"type":"writer","name":"Test writeerrr"}],"processors":[],"rightsholders":[]},"tags":{"tags":["fraktureringstrykk","poretrykk","reservoartrykk"],"language":"nb"},"caption":{"caption":"","language":"nb"},"supportedLanguages":["nb","en","und"],"created":"2017-05-08T13:25:26.000Z","createdBy":"content-import-client","modelRelease":"not-set","image":{"fileName":"poretrykkgradient1.jpg","size":1171953,"contentType":"image/jpeg","imageUrl":"https://api.test.ndla.no/image-api/raw/poretrykkgradient1.jpg","dimensions":{"width":4090,"height":2045},"language":"nb"}},{"id":"154","metaUrl":"https://api.test.ndla.no/image-api/v3/images/154","title":{"title":"Okse av rasen Limousin","language":"und"},"alttext":{"alttext":"Okse av rasen Limousin. Foto.","language":"und"},"copyright":{"license":{"license":"CC-BY-NC-ND-4.0","description":"Creative Commons Attribution-NonCommercial-NoDerivs 4.0 International","url":"https://creativecommons.org/licenses/by-nc-nd/4.0/"},"origin":"Test User","creators":[{"type":"Writer","name":"Test writer"},{"type":"writer","name":"Test writeerrr"}],"processors":[],"rightsholders":[]},"tags":{"tags":["husdyravl","kjøttfe","limousin","storfe"],"language":"nb"},"caption":{"caption":"","language":"nb"},"supportedLanguages":["nb","nn","en","und"],"created":"2017-05-08T13:25:26.000Z","createdBy":"content-import-client","modelRelease":"not-set","image":{"fileName":"20031028sg2011.jpg","size":318059,"contentType":"image/jpeg","imageUrl":"https://api.test.ndla.no/image-api/raw/20031028sg2011.jpg","dimensions":{"width":920,"height":613},"language":"nb"}},{"id":"220","metaUrl":"https://api.test.ndla.no/image-api/v3/images/220","title":{"title":"Blåkorg","language":"und"},"alttext":{"alttext":"Blåkorg. Foto.","language":"und"},"copyright":{"license":{"license":"CC-BY-NC-ND-4.0","description":"Creative Commons Attribution-NonCommercial-NoDerivs 4.0 International","url":"https://creativecommons.org/licenses/by-nc-nd/4.0/"},"origin":"Test User","creators":[{"type":"Writer","name":"Test writer"},{"type":"writer","name":"Test writeerrr"}],"processors":[],"rightsholders":[]},"tags":{"tags":["ageratum houstonianum","sommerblomster","utplantingsplanter"],"language":"nb"},"caption":{"caption":"","language":"nb"},"supportedLanguages":["nb","nn","und"],"created":"2017-05-08T13:25:26.000Z","createdBy":"content-import-client","modelRelease":"not-set","image":{"fileName":"csm_ageratum_houstonianum_e46ad4a6c4.png","size":1090184,"contentType":"image/png","imageUrl":"https://api.test.ndla.no/image-api/raw/csm_ageratum_houstonianum_e46ad4a6c4.png","dimensions":{"width":752,"height":1000},"language":"nb"}}]}