[{"id":"urn:resourcetype:learningPath","name":"Læringssti","translations":[{"name":"Oahppanbálggis","language":"se"},{"name":"Learning Path","language":"en"},{"name":"Læringssti","language":"nn"},{"name":"Læringssti","language":"nb"}],"supportedLanguages":["nn","se","nb","en"]},{"id":"urn:resourcetype:subjectMaterial","name":"Fagstoff","subtypes":[{"id":"urn:resourcetype:toolAndTemplate","name":"Verktøy og mal","translations":[{"name":"Tools and Templates","language":"en"},{"name":"Verktøy og mal","language":"nb"},{"name":"Verktøy og mal","language":"nn"},{"name":"Reaiddut ja málle","language":"se"}],"supportedLanguages":["nn","se","nb","en"]},{"id":"urn:resourcetype:movieAndClip","name":"Film og filmklipp","translations":[{"name":"Film og filmklipp","language":"nn"},{"name":"Film og filmklipp","language":"nb"},{"name":"Films and Film clips","language":"en"},{"name":"Filmmat ja filbmaoasážat","language":"se"}],"supportedLanguages":["nn","se","nb","en"]},{"id":"urn:resourcetype:academicArticle","name":"Fagartikkel","translations":[{"name":"Fagartikkel","language":"nn"},{"name":"Fágaartihkal","language":"se"},{"name":"Article","language":"en"},{"name":"Fagartikkel","language":"nb"}],"supportedLanguages":["nn","se","nb","en"]},{"id":"urn:resourcetype:guidance","name":"Veiledning","translations":[{"name":"Bagadus","language":"se"},{"name":"Rettleiing","language":"nn"},{"name":"Veiledning","language":"nb"},{"name":"Guidance","language":"en"}],"supportedLanguages":["nn","se","nb","en"]},{"id":"urn:resourcetype:soundRecording","name":"Lydopptak","translations":[{"name":"Lydopptak","language":"nb"},{"name":"Sound Recordings","language":"en"},{"name":"Jietnabádden","language":"se"},{"name":"Lydopptak","language":"nn"}],"supportedLanguages":["nn","se","nb","en"]},{"id":"urn:resourcetype:simulation","name":"Simulering","translations":[{"name":"Simulering","language":"nb"},{"name":"Simulations","language":"en"},{"name":"Simulering","language":"nn"},{"name":"Simuleren","language":"se"}],"supportedLanguages":["nn","se","nb","en"]},{"id":"urn:resourcetype:dictionary","name":"Oppslagsverk og ordliste","translations":[{"name":"Oppslagsverk og ordliste","language":"nn"},{"name":"Oppslagsverk og ordliste","language":"nb"},{"name":"Dictionary","language":"en"},{"name":"Diehtogirjjit ja sátnegirji","language":"se"}],"supportedLanguages":["nn","se","nb","en"]},{"id":"urn:resourcetype:lectureAndPresentation","name":"Forelesing og presentasjon","translations":[{"name":"Logaldallan ja ovdanbuktin","language":"se"},{"name":"Førelesing og presentasjon","language":"nn"},{"name":"Lectures and Presentations","language":"en"},{"name":"Forelesing og presentasjon","language":"nb"}],"supportedLanguages":["nn","se","nb","en"]}],"translations":[{"name":"Fagstoff","language":"nn"},{"name":"Subject Material","language":"en"},{"name":"Fagstoff","language":"nb"},{"name":"Fágaávnnas","language":"se"}],"supportedLanguages":["nn","se","nb","en"]},{"id":"urn:resourcetype:tasksAndActivities","name":"Oppgaver og aktiviteter","subtypes":[{"id":"urn:resourcetype:game","name":"Spill","translations":[{"name":"Speallu","language":"se"},{"name":"Spill","language":"nb"},{"name":"Spel","language":"nn"},{"name":"Game","language":"en"}],"supportedLanguages":["nn","se","nb","en"]},{"id":"urn:resourcetype:task","name":"Oppgåve","translations":[{"name":"Oppgave","language":"nn"},{"name":"Task","language":"en"},{"name":"Oppgåve","language":"nb"},{"name":"Bargobihttá","language":"se"}],"supportedLanguages":["nn","se","nb","en"]},{"id":"urn:resourcetype:exercise","name":"Øvelse","translations":[{"name":"Hárjehus","language":"se"},{"name":"Øvelse","language":"nb"},{"name":"Øving","language":"nn"},{"name":"Exercise","language":"en"}],"supportedLanguages":["nn","se","nb","en"]},{"id":"urn:resourcetype:workAssignment","name":"Arbeidsoppdrag","translations":[{"name":"Work Assignment","language":"en"},{"name":"Arbeidsoppdrag","language":"nn"},{"name":"Arbeidsoppdrag","language":"nb"},{"name":"Bargodoaibma","language":"se"}],"supportedLanguages":["nn","se","nb","en"]},{"id":"urn:resourcetype:experiment","name":"Forsøk","translations":[{"name":"Forsøk","language":"nn"},{"name":"Geahččaladdan","language":"se"},{"name":"Experiment","language":"en"},{"name":"Forsøk","language":"nb"}],"supportedLanguages":["nn","se","nb","en"]}],"translations":[{"name":"Oppgaver og aktiviteter","language":"nb"},{"name":"Oppgåver og aktivitetar","language":"nn"},{"name":"Bargobihtát ja doaimmat","language":"se"},{"name":"Tasks and Activites","language":"en"}],"supportedLanguages":["nn","se","nb","en"]},{"id":"urn:resourcetype:reviewResource","name":"Vurderingsressurs","subtypes":[{"id":"urn:resourcetype:selfEvaluation","name":"Egenvurdering","translations":[{"name":"Self Evaluation","language":"en"},{"name":"Eigenvurdering","language":"nn"},{"name":"Iežas árvvoštallan","language":"se"},{"name":"Egenvurdering","language":"nb"}],"supportedLanguages":["nn","se","nb","en"]}],"translations":[{"name":"Vurderingsressurs","language":"nb"},{"name":"Assessment Resources","language":"en"},{"name":"Vurderingsressurs","language":"nn"},{"name":"Árvvoštallanresursa","language":"se"}],"supportedLanguages":["nn","se","nb","en"]},{"id":"urn:resourcetype:SourceMaterial","name":"Kildemateriell","subtypes":[{"id":"urn:resourcetype:shortFilm","name":"Kortfilm","translations":[{"name":"Short Film","language":"en"},{"name":"Oanehisfilbma","language":"se"},{"name":"Kortfilm","language":"nb"},{"name":"Kortfilm","language":"nn"}],"supportedLanguages":["nn","se","nb","en"]},{"id":"urn:resourcetype:series","name":"Serier","translations":[{"name":"Serier","language":"nb"},{"name":"Series","language":"en"},{"name":"Ráiddut","language":"se"},{"name":"Seriar","language":"nn"}],"supportedLanguages":["nn","se","nb","en"]},{"id":"urn:resourcetype:historicalMaterial","name":"Historisk materiale","translations":[{"name":"Historiske kjelder","language":"nn"},{"name":"Historisk materiale","language":"nb"},{"name":"Historical Sources","language":"en"},{"name":"Historjjálaš materiála","language":"se"}],"supportedLanguages":["nn","se","nb","en"]},{"id":"urn:resourcetype:filmClip","name":"Filmklipp","translations":[{"name":"Filmklipp","language":"nb"},{"name":"Filmklipp","language":"nn"},{"name":"Film Clip","language":"en"},{"name":"Filbmaoasáš","language":"se"}],"supportedLanguages":["nn","se","nb","en"]},{"id":"urn:resourcetype:documentary","name":"Doumentarfilm","translations":[{"name":"Doumentarfilm","language":"nb"},{"name":"Doumentarfilm","language":"nn"},{"name":"Dokumentára filbma","language":"se"},{"name":"Documentary","language":"en"}],"supportedLanguages":["nn","se","nb","en"]},{"id":"urn:resourcetype:featureFilm","name":"Spillefilm","translations":[{"name":"Spelefilm","language":"nn"},{"name":"Spillefilm","language":"nb"},{"name":"Guoimmuhanfilbma","language":"se"},{"name":"Feature Film","language":"en"}],"supportedLanguages":["nn","se","nb","en"]},{"id":"urn:resourcetype:literaryText","name":"Litterære tekster","translations":[{"name":"Literary Text","language":"en"},{"name":"Litterære tekstar","language":"nn"},{"name":"Girjjálašvuođa teavsttat","language":"se"},{"name":"Litterære tekster","language":"nb"}],"supportedLanguages":["nn","se","nb","en"]}],"translations":[{"name":"Gáldomateriála","language":"se"},{"name":"External resources","language":"en"},{"name":"Kjeldemateriale","language":"nn"},{"name":"Kildemateriell","language":"nb"}],"supportedLanguages":["nn","se","nb","en"]}]